adafruit_tca8418.py
adafruit_circuitpython_tca8418-1.0.19.dist-info/licenses/LICENSE
adafruit_circuitpython_tca8418-1.0.19.dist-info/METADATA
adafruit_circuitpython_tca8418-1.0.19.dist-info/WHEEL
adafruit_circuitpython_tca8418-1.0.19.dist-info/top_level.txt
adafruit_circuitpython_tca8418-1.0.19.dist-info/RECORD
