Metadata-Version: 2.4
Name: adafruit-circuitpython-tca8418
Version: 1.0.19
Summary: CircuitPython / Python library for TCA8418 Keyboard Multiplexor
Author-email: Adafruit Industries <circuitpython@adafruit.com>
License: MIT
Project-URL: Homepage, https://github.com/adafruit/Adafruit_CircuitPython_TCA8418.git
Keywords: adafruit,blinka,circuitpython,micropython,tca8418,python,keyboard,keeb
Classifier: Intended Audience :: Developers
Classifier: Topic :: Software Development :: Libraries
Classifier: Topic :: Software Development :: Embedded Systems
Classifier: Topic :: System :: Hardware
Classifier: License :: OSI Approved :: MIT License
Classifier: Programming Language :: Python :: 3
License-File: LICENSE
Requires-Dist: Adafruit-Blinka
Requires-Dist: adafruit-circuitpython-busdevice
Requires-Dist: adafruit-circuitpython-register
Provides-Extra: optional
Requires-Dist: adafruit-circuitpython-debug-i2c; extra == "optional"
Dynamic: license-file
